pywaclient/__init__.py
pywaclient/api.py
pywaclient/endpoints/__init__.py
pywaclient/endpoints/articles.py
pywaclient/endpoints/block_templates.py
pywaclient/endpoints/blocks.py
pywaclient/endpoints/canvas.py
pywaclient/endpoints/categories.py
pywaclient/endpoints/chronicles.py
pywaclient/endpoints/eras.py
pywaclient/endpoints/histories.py
pywaclient/endpoints/images.py
pywaclient/endpoints/manuscripts.py
pywaclient/endpoints/map_marker_types.py
pywaclient/endpoints/maps.py
pywaclient/endpoints/notebooks.py
pywaclient/endpoints/rpg_system.py
pywaclient/endpoints/secrets.py
pywaclient/endpoints/subscriber_groups.py
pywaclient/endpoints/timelines.py
pywaclient/endpoints/users.py
pywaclient/endpoints/variables.py
pywaclient/endpoints/worlds.py
pywaclient/exceptions/__init__.py
pywaclient-1.6.8.dist-info/LICENCE
pywaclient-1.6.8.dist-info/METADATA
pywaclient-1.6.8.dist-info/WHEEL
pywaclient-1.6.8.dist-info/top_level.txt
pywaclient-1.6.8.dist-info/RECORD
