Metadata-Version: 2.1
Name: pywaclient
Version: 1.6.8
Summary: A simple wrapper client library for the World Anvil API.
Home-page: https://gitlab.com/SoulLink/world-anvil-api-client
Author: Jonas Waeber
Author-email: jonaswaeber@gmail.com
License: Apache 2.0
Platform: UNKNOWN
Classifier: Programming Language :: Python :: 3.7
License-File: LICENCE
Requires-Dist: requests
